[
    {
        "question": "Apa itu Madrasah Diniyyah Salafiyyah?",
        "answer": "Madrasah Diniyyah Salafiyyah adalah lembaga pendidikan keagamaan yang mengajarkan ilmu-ilmu dasar Islam dengan kurikulum klasik."
    },
    {
        "question": "Siapa saja yang bisa mendaftar?",
        "answer": "Kami membuka pendaftaran untuk semua anak-anak muslim usia sekolah dasar hingga menengah."
    },
    {
        "question": "Apakah ada biaya pendaftaran?",
        "answer": "Ada, namun kami menyediakan beasiswa untuk siswa yang membutuhkan."
    },
    {
        "question": "Kapan waktu belajarnya?",
        "answer": "Waktu belajar umumnya sore hingga malam hari, menyesuaikan dengan kegiatan sekolah formal."
    }
]